Workbook

Sheet 00_Cover
B2: GOLDMAN SACHS | INVESTMENT BANKING DIVISION
B4: Mergers & Acquisitions — Due Diligence Memorandum
B5: Post-2021 M&A Case Study: One Success, One Failure
B6: Success: Mars, Incorporated — Acquisition of Kellanova (NYSE: K) | Failure: Reliance Retail — Strategic Investment in Dunzo
B10: Primary DD subject | C10: Mars, Inc. acquisition of Kellanova
B11: Presentation currency | C11: Indian Rupee (INR); principal unit = INR crore (1 crore = 10 million)
B12: FX assumption | C12: USD/INR = 83.97 as of deal announcement date 14-Aug-2024 (see 09_Assumptions_Sources)
B14: Assignment Brief
B15: 1) Identify two M&A cases after 2021 — one that failed and one that succeeded — and explain the reasons for failure / success in terms of synergies. 2) Perform due diligence on one case (Mars–Kellanova) and assess whether the M&A consideration amount was justifiable.

Sheet 01_Executive_Summary
B2: Executive Summary
B3: Conclusions for both post-2021 cases and the fairness view on the Mars–Kellanova consideration. All values in INR crore unless stated.
B5: Mars–Kellanova — Headline Deal Economics (INR crore unless noted)
B6: Metric | C6: Value | D6: Unit | E6: Note / Source
B7: Total consideration (Enterprise Value) | C7: =35.9*1000*'08_Assumptions_Sources'!$D$9 -> 301452.3 | D7: INR cr | E7: $35.9bn EV × FX factor (S1, S2)
B8: Offer price per share | C8: =83.5*'08_Assumptions_Sources'!$D$7 -> 7011.495 | D8: INR/sh | E8: $83.50/share all-cash × FX (S1, S2)
B9: Premium to 30-day VWAP | C9: 0.44 | D9: % | E9: Stated 44% premium (S1, S2)
B10: Premium to 52-week high | C10: 0.33 | D10: % | E10: Stated 33% premium (S1, S2)
B11: Implied EV / LTM adj. EBITDA | C11: 16.4 | D11: x | E11: Stated multiple (S1, S2)
B12: Debt-funded share of financing | C12: 0.864 | D12: % | E12: $31bn of $35.9bn (S1)
B14: Verdicts at a Glance
B15: Case | C15: Status | D15: One-line verdict
B16: Mars, Inc. → Kellanova | C16: SUCCESS / STRATEGICALLY STRONG | D16: Compelling scale, portfolio, distribution and brand synergies; full-cash 44% premium is rich but justifiable given strategic control value and Mars' financing capacity. Success is contingent on execution and deleveraging.
B17: Reliance Retail → Dunzo | C17: FAILURE / UNDER-REALISED | D17: Synergies never materialised: persistent cash burn, weak unit economics, integration gaps and intense quick-commerce competition led Reliance to write off its ~₹1,645 cr stake (S8).
B19: Why Each Deal Succeeded / Failed (Synergy Lens)
B20: Dimension | C20: Mars–Kellanova (Success driver) | D20: Reliance–Dunzo (Failure driver)
B21: Financial | C21: Scale play: combined ~$36bn snacking revenue; procurement & cash-flow synergies support deleveraging (S1,S2). | F21: Cash burn >₹100 cr/month; revenue could not offset losses (FY23 loss ~₹1,800 cr) (S8,S9).
B22: Operational | C22: Complementary distribution, supply chain and R&D across 180 markets; ~23k + 150k associates (S1,S2). | F22: Tech/inventory systems unaligned; integration incomplete; corporate-vs-startup culture clash (S1).
B23: Strategic | C23: Two new $1bn brands (Pringles, Cheez-It); stronger vs PepsiCo/Mondelez (S1,S2). | F23: Competitors (Blinkit, Zepto, Instamart) scaled faster; Dunzo lost relevance and was written off (S8,S10).
B25: Final Fairness View — Mars–Kellanova Consideration
B26: Conclusion: the ~₹3.01 lakh-crore (US$35.9bn) consideration was JUSTIFIABLE BUT NOT CHEAP. At 16.4x LTM adjusted EBITDA and a 44% premium to the unaffected 30-day VWAP, Mars paid a full strategic-control price — above typical packaged-food trading multiples (~12–15x). It is defensible because (i) the all-cash certainty secured a clean exit and board/foundation support, (ii) Mars gains two new billion-dollar brands and a doubling of its snacking platform, and (iii) Mars' private balance sheet and cash flows can absorb the leverage (peaking ~4.0x, falling <3.0x by FY2027). The premium is best viewed as payment for strategic option value and synergy potential rather than for current standalone cash flows. See 07_Consideration_Fairness for the framework.

Sheet 02_Case_Comparison
B2: Case Comparison — Two Post-2021 M&A Deals
B3: Side-by-side comparison of the successful and failed cases. USD values converted to INR using FX = 83.97 (deal-date basis).
B5: Side-by-Side Comparison
B6: Attribute | C6: Case 1 — SUCCESS | D6: Case 2 — FAILURE
B7: Acquirer | C7: Mars, Incorporated (private, family-owned) | D7: Reliance Retail (Reliance Industries)
B8: Target | C8: Kellanova (NYSE: K) | D8: Dunzo (hyperlocal / quick-commerce startup)
B9: Announcement / deal date | C9: 14-Aug-2024 (closed 11-Dec-2025) | D9: January 2022 (strategic investment round)
B10: Structure | C10: All-cash acquisition (100%) | D10: Minority strategic equity investment
B11: Stake / consideration | C11: 100% for $83.50/share = $35.9bn EV → ₹301,452 cr | D11: ~25.8–26% stake for ~₹1,645 cr (part of $240m round)
B12: Implied valuation metric | C12: 16.4x LTM adj. EBITDA; 44% premium to 30-day VWAP | D12: Loss-making; venture-style growth valuation
B13: Status / outcome | C13: Completed; strategically strong, execution-dependent | D13: Investment written off (FY25); Dunzo wound down
B14: Expected synergies | C14: Scale (~$36bn snacking), distribution, R&D, 2 new $1bn brands | D14: Quick-commerce entry, last-mile logistics for JioMart, dark-store scale
B15: Realised / unrealised synergies | C15: Largely intact at close; realisation in progress | D15: Largely unrealised — burn, weak unit economics, integration gaps
B16: Primary success / failure reason | C16: Strong strategic fit + scale + financing capacity | D16: Unsustainable cash burn + competition + integration failure
B17: Key risk | C17: Leverage (~4.0x peak) & multi-country integration | D17: Quick-commerce economics & competitive intensity
B18: Source IDs | C18: S1, S2, S3, S5 | D18: S1, S8, S9, S10

Sheet 03_Mars_Kellanova_DD
B2: Mars–Kellanova — Due Diligence Findings
B3: Qualitative and quantitative diligence across seven workstreams. Numbers reference 04_Kellanova_Financials and 05_Deal_Terms_Valuation. Sources in 09_Assumptions_Sources.
B5: Due Diligence Workstreams
B6: Workstream | C6: Finding
B7: Strategic rationale | C7: Mars converts a confectionery + pet-care platform into a full-spectrum global snacking leader, targeting a doubling of Mars Snacking over the next decade. Kellanova adds a ~$13bn revenue base across 180 markets, bringing the combined snacking platform to ~$36bn and strengthening Mars vs PepsiCo and Mondelez. Adds two new $1bn brands — Pringles and Cheez-It — plus Pop-Tarts, RXBAR, NutriGrain, Eggo, MorningStar Farms (S1, S2).
B8: Target business profile | C8: Kellanova (post Kellogg split, Oct-2023) is a branded CPG manufacturer/marketer of snacks and convenience foods, sold via direct sales teams, brokers and distributors. FY2024 net sales $12,749m (₹107,053 cr), operating profit $1,873m, net income $1,343m (S3). Reportable segments: North America, Europe, Latin America, AMEA.
B9: Product / geography / customer concentration | C9: Product: salty snacks, crackers, toaster pastries, cereal bars, international cereal, noodles, frozen breakfast, plant-based. Geography: manufacturing in ~20 countries; products sold in 180+ countries. Customer concentration is a key risk: Walmart ~16% of FY2024 net sales (~$2.04bn) and top-5 customers ~29% (~$3.70bn), ~46% of US net sales (S4). See 04 for INR values.
B10: Operational diligence | C10: ~23,000–24,000 Kellanova employees and 32+ million sq. ft. of facilities join Mars' 150,000+ associates. Largely unionised manufacturing/distribution network — integration must avoid disruption. Complementary supply chains and R&D, with notable white space in Africa and Latin America where Mars distribution can scale Kellanova brands (S1, S2, S4).
B11: Financial diligence | C11: Quality of earnings: FY2024 operating profit grew to $1,873m from $1,505m (FY2023) with operating margin ~14.7% — consistent with Kellanova's >15% adjusted operating-margin target. Net debt $5,049m (FY2024). Implied LTM adjusted EBITDA ~$2.19bn (back-solved from $35.9bn ÷ 16.4x). Cash $694m provides modest standalone liquidity (S3, A4). See 04 & 05.
B12: Management / ownership / regulatory | C12: All-cash deal unanimously approved by Kellanova's Board; W.K. Kellogg Foundation Trust (~20.7% of shares) agreed to vote in favour; shareowner approval 01-Nov-2024. Closing required 28 regulatory approvals across jurisdictions (closed 11-Dec-2025). Antitrust focus on combined bargaining power with large retailers (S1, S2).
B13: Integration risks | C13: (i) Leverage: pro-forma rises from ~1.2x (FY2024) to ~4.0x at close, targeted <3.0x by FY2027 — S&P downgraded Mars A+→A. (ii) Multi-country workforce/facility integration. (iii) Retailer concentration (Walmart). (iv) Culture/operating-model alignment between a private family company and a listed CPG. Detailed in 08_PMI_Risks_Mitigants (S1, S5).

Sheet 04_Kellanova_Financials
B2: Kellanova — Historical Financial Snapshot
B3: Source figures reported in USD millions (Kellanova FY2024 results, S3); converted to INR crore at FX = 83.97 (1 USD mn = ₹8.397 cr). Margins are live formulas.
B5: Income Statement & Balance Sheet (USD mn reported → INR crore)
B6: Line item | C6: FY2023 (USD mn) | D6: FY2024 (USD mn) | E6: FY2023 (INR cr) | F6: FY2024 (INR cr) | G6: YoY % (INR) | H6: Source / note
B7: Net sales | C7: 13122 | D7: 12749 | E7: =C7*'08_Assumptions_Sources'!$D$9 -> 110185.43 | F7: =D7*'08_Assumptions_Sources'!$D$9 -> 107053.35 | G7: =(F7-E7)/E7 -> -0.028425545 | H7: Kellanova FY24 results (S3)
B8: Gross profit | C8: 4283 | D8: 4544 | E8: =C8*'08_Assumptions_Sources'!$D$9 -> 35964.351 | F8: =D8*'08_Assumptions_Sources'!$D$9 -> 38155.968 | G8: =(F8-E8)/E8 -> 0.060938594 | H8: Kellanova FY24 results (S3)
B9: Operating profit | C9: 1505 | D9: 1873 | E9: =C9*'08_Assumptions_Sources'!$D$9 -> 12637.485 | F9: =D9*'08_Assumptions_Sources'!$D$9 -> 15727.581 | G9: =(F9-E9)/E9 -> 0.24451827 | H9: Kellanova FY24 results (S3)
B10: Net income (attrib. to Kellanova) | C10: 951 | D10: 1343 | E10: =C10*'08_Assumptions_Sources'!$D$9 -> 7985.547 | F10: =D10*'08_Assumptions_Sources'!$D$9 -> 11277.171 | G10: =(F10-E10)/E10 -> 0.41219769 | H10: Kellanova FY24 results (S3)
B11: Adjusted EBITDA (LTM, implied) | C11: N/A | D11: 2188 | E11: N/A | F11: =D11*'08_Assumptions_Sources'!$D$9 -> 18372.636 | G11: N/A | H11: Implied = $35.9bn ÷ 16.4x (A4, S2)
B13: Profitability Margins (live formulas, % of net sales)
B14: Margin | C14: FY2023 % | D14: FY2024 % | E14: Δ (pp) | H14: Basis
B15: Gross margin | C15: =C8/C7 -> 0.32639841 | D15: =D8/D7 -> 0.35642011 | E15: =(D8/D7-C8/C7) -> 0.030021697 | H15: Gross profit ÷ Net sales
B16: Operating margin | C16: =C9/C7 -> 0.11469288 | D16: =D9/D7 -> 0.14691348 | E16: =(D9/D7-C9/C7) -> 0.032220601 | H16: Operating profit ÷ Net sales
B17: Net margin | C17: =C10/C7 -> 0.072473708 | D17: =D10/D7 -> 0.1053416 | E17: =(D10/D7-C10/C7) -> 0.032867887 | H17: Net income ÷ Net sales
B19: Balance Sheet — Liquidity & Leverage (USD mn → INR cr)
B20: Item | C20: FY2023 (USD mn) | D20: FY2024 (USD mn) | E20: FY2023 (INR cr) | F20: FY2024 (INR cr) | H20: Source / note
B21: Cash & cash equivalents | C21: 274 | D21: 694 | E21: =C21*'08_Assumptions_Sources'!$D$9 -> 2300.778 | F21: =D21*'08_Assumptions_Sources'!$D$9 -> 5827.518 | H21: Kellanova FY24 results, balance sheet (S3)
B22: Total debt liabilities | C22: 5873 | D22: 5743 | E22: =C22*'08_Assumptions_Sources'!$D$9 -> 49315.581 | F22: =D22*'08_Assumptions_Sources'!$D$9 -> 48223.971 | H22: Kellanova FY24 results, balance sheet (S3)
B23: Net debt | C23: 5599 | D23: 5049 | E23: =C23*'08_Assumptions_Sources'!$D$9 -> 47014.803 | F23: =D23*'08_Assumptions_Sources'!$D$9 -> 42396.453 | H23: Kellanova FY24 results, balance sheet (S3)
B25: Customer Concentration (FY2024, S4)
B26: Customer / group | C26: % of net sales | D26: Implied INR cr | H26: Source / note
B27: Walmart | C27: 0.16 | D27: =C27*F7 -> 17128.536 | H27: Kellanova FY24 10-K customer concentration (S4)
B28: Top 5 customers | C28: 0.29 | D28: =C28*F7 -> 31045.472 | H28: Kellanova FY24 10-K customer concentration (S4)

Sheet 05_Deal_Terms_Valuation
B2: Mars–Kellanova — Deal Terms & Valuation
B3: Deal economics with live formulas. USD inputs (blue) sourced from S1/S2; INR conversions use FX = 83.97 (cell linked to Assumptions A1).
B5: Transaction Inputs (sourced)
B6: Item | C6: Value (USD) | D6: Unit | E6: Value (INR) | F6: Unit | G6: Source / note
B7: Offer price per share | C7: 83.5 | D7: USD/sh | E7: =C7*'08_Assumptions_Sources'!$D$7 -> 7011.495 | F7: INR/sh | G7: $83.50 all-cash (S1, S2)
B8: Enterprise value / consideration | C8: 35900 | D8: USD mn | E8: =C8*'08_Assumptions_Sources'!$D$9 -> 301452.3 | F8: INR cr | G8: $35.9bn incl. assumed net leverage (S1, S2)
B9: Debt financing (total) | C9: 31000 | D9: USD mn | E9: =C9*'08_Assumptions_Sources'!$D$9 -> 260307 | F9: INR cr | G9: $31bn = 86.4% of financing (S1)
B10: of which: Senior notes | C10: 26000 | D10: USD mn | E10: =C10*'08_Assumptions_Sources'!$D$9 -> 218322 | F10: INR cr | G10: $26bn senior notes, 4.450%–5.800% coupons (S1, S5)
B11: of which: Private placement notes | C11: 1000 | D11: USD mn | E11: =C11*'08_Assumptions_Sources'!$D$9 -> 8397 | F11: INR cr | G11: $1bn-equiv. private placement (S1)
B12: of which: Delayed-draw term loans | C12: 4000 | D12: USD mn | E12: =C12*'08_Assumptions_Sources'!$D$9 -> 33588 | F12: INR cr | G12: $4bn delayed-draw term loans (S1)
B13: Cash / internal resources | C13: 4900 | D13: USD mn | E13: =C13*'08_Assumptions_Sources'!$D$9 -> 41145.3 | F13: INR cr | G13: $4.9bn = 13.6% cash on hand (S1)
B14: LTM adjusted EBITDA (implied) | C14: 2188 | D14: USD mn | E14: =C14*'08_Assumptions_Sources'!$D$9 -> 18372.636 | F14: INR cr | G14: Implied = EV ÷ 16.4x (A4)
B16: Derived Valuation Metrics (live formulas)
B17: Metric | C17: Result | D17: Unit | G17: Basis
B18: Premium to 30-day VWAP | C18: 0.44 | D18: % | G18: Stated (S1, S2)
B19: Premium to 52-week high | C19: 0.33 | D19: % | G19: Stated (S1, S2)
B20: Implied EV / LTM adj. EBITDA | C20: =C8/C14 -> 16.407678 | D20: x | G20: EV ÷ implied EBITDA (≈16.4x) (S1)
B21: Debt-funded share of financing | C21: =C9/C8 -> 0.86350975 | D21: % | G21: $31bn ÷ $35.9bn (S1)
B22: Cash-funded share of financing | C22: =C13/C8 -> 0.13649025 | D22: % | G22: $4.9bn ÷ $35.9bn (S1)
B23: Senior-notes annual interest @5.14% | C23: =C10*0.0514*'08_Assumptions_Sources'!$D$9 -> 11221.751 | D23: INR cr | G23: $26bn × 5.14% wtd coupon → ₹ (S1, S5)
B24: EV in INR (₹ lakh crore) | C24: =E8/100000 -> 3.014523 | D24: ₹ lakh cr | G24: Consideration scale check
B26: Financing Mix & Leverage Effect
B27: Financing tranche | C27: USD mn | D27: % of total | E27: INR cr
B28: Senior notes | C28: =C10 -> 26000 | D28: =C10/C$8 -> 0.72423398 | E28: =C28*'08_Assumptions_Sources'!$D$9 -> 218322
B29: Private placement notes | C29: =C11 -> 1000 | D29: =C11/C$8 -> 0.027855153 | E29: =C29*'08_Assumptions_Sources'!$D$9 -> 8397
B30: Delayed-draw term loans | C30: =C12 -> 4000 | D30: =C12/C$8 -> 0.11142061 | E30: =C30*'08_Assumptions_Sources'!$D$9 -> 33588
B31: Cash on hand / internal | C31: =C13 -> 4900 | D31: =C13/C$8 -> 0.13649025 | E31: =C31*'08_Assumptions_Sources'!$D$9 -> 41145.3
B32: Total financing | C32: =SUM(C28:C31) -> 35900 | D32: =SUM(D28:D31) -> 1 | E32: =SUM(E28:E31) -> 301452.3
B34: Leverage Path (S&P-noted, S1/S5)
B35: Leverage milestone | C35: Net debt / EBITDA (x) | G35: Note
B36: Mars pre-deal (FY2024) | C36: 1.2 | F36: S&P A+ pre-deal (S5)
B37: At close (~FY2025) | C37: 4 | F37: S&P downgrade A+→A (S5)
B38: Target by FY2027 | C38: 3 | F38: Cash-flow deleveraging target (S1)

Sheet 06_Synergy_Assessment
B2: Synergy Assessment — Both Cases
B3: Expected vs actual/likely realisation, scored 1 (none) to 5 (fully realised). Mars success is execution-dependent; Dunzo synergies under-realised.
H4: Synergy Scorecard (chart data)
B5: Mars–Kellanova (Success — strategic & scale synergy)
B6: Synergy category | C6: Expected synergy | D6: Actual / likely realisation | E6: Score (1-5) | F6: Status | H6: Category | I6: Mars | J6: Dunzo
B7: Financial | C7: Scale to ~$36bn snacking revenue; procurement efficiencies; cash-flow-driven deleveraging (S1,S2). | D7: Strong rationale; realisation depends on deleveraging from ~4.0x to <3.0x by FY27. Not seasoned at close. | E7: 4 | F7: On track | H7: Financial | I7: =E7 -> 4 | J7: =E15 -> 1
B8: Operational | C8: Complementary distribution, supply chain, R&D across 180 markets; Africa & LatAm white space (S1,S2). | D8: High potential; multi-country, unionised integration adds execution risk. | E8: 4 | F8: On track | H8: Operational | I8: =E8 -> 4 | J8: =E16 -> 2
B9: Strategic | C9: Two new $1bn brands (Pringles, Cheez-It); stronger vs PepsiCo/Mondelez; Gen-Z/Millennial relevance (S1,S2). | D9: Clear and largely structural — realised at deal logic level immediately. | E9: 5 | F9: Realised | H9: Strategic | I9: =E9 -> 5 | J9: =E17 -> 1
B10: Revenue / cross-sell | C10: Brand monetisation via Mars' global infrastructure and investment capacity (S2). | D10: Credible medium-term upside; requires commercial integration. | E10: 4 | F10: On track | H10: Revenue/Talent | I10: =E10 -> 4 | J10: =E18 -> 1
B11: Average score | C11: Weighted toward strong strategic/scale synergy | E11: =AVERAGE(E7:E10) -> 4.25 | F11: SUCCESS
B13: Reliance–Dunzo (Failure — synergies under-realised)
B14: Synergy category | C14: Expected synergy | D14: Actual outcome | E14: Score (1-5) | F14: Status
B15: Financial | C15: Revenue growth, cross-sell, better monetisation, lower logistics cost via scale (S1). | D15: Cash burn >₹100cr/month; FY23 loss ~₹1,800cr; revenue ~₹89–226cr could not offset losses (S8,S9,S10). | E15: 1 | F15: Failed
B16: Operational | C16: Shared dark stores, route optimisation, inventory & warehousing integration (S1). | D16: Tech/inventory systems unaligned; integration incomplete; culture mismatch (S1). | E16: 2 | F16: Under-realised
B17: Strategic | C17: National quick-commerce ecosystem; stronger vs Amazon/Blinkit; accelerate JioMart (S1). | D17: Competitors scaled faster; Dunzo lost relevance; Reliance refocused on own ecosystem (S1,S10). | E17: 1 | F17: Failed
B18: Talent / execution | C18: Retain logistics talent; fast execution (S1). | D18: Layoffs (150+), salary delays, leadership uncertainty (S8,S9). | E18: 1 | F18: Failed
B19: Average score | C19: Synergies largely unrealised; stake written off (₹1,645cr) | E19: =AVERAGE(E15:E18) -> 1.25 | F19: FAILURE

Sheet 07_Consideration_Fairness
B2: Consideration Fairness — Mars–Kellanova
B3: Fairness framework and EBITDA-multiple sensitivity. All INR crore. EBITDA & EV link to 05_Deal_Terms_Valuation; FX via Assumptions.
B5: Fairness Framework
B6: Fairness factor | C6: Observation | D6: Verdict / weight
B7: Deal multiple vs peers | C7: 16.4x LTM adj. EBITDA vs packaged-food trading comps ~12–15x — at/above range (S1,S2). | G7: Rich but within control-premium norms
B8: Revenue / profit base | C8: FY24 net sales $12.7bn; operating profit $1.87bn; net income $1.34bn — solid, growing base (S3). | G8: Supports valuation
B9: Strategic control premium | C9: 44% to 30-day VWAP; 33% to 52-week high — payment for 100% control + synergy option value (S1,S2). | G9: Justifiable for strategic buyer
B10: Synergy rationale | C10: Scale to ~$36bn snacking, 2 new $1bn brands, distribution/R&D synergies (S1,S2). | G10: Strong qualitative support
B11: Financing capacity / leverage | C11: All-cash; $31bn debt; leverage ~4.0x peak → <3.0x by FY27; S&P A (S1,S5). | G11: Affordable for Mars' cash flows
B12: Risks | C12: Integration across 180 markets; Walmart concentration; deleveraging; regulatory (S4). | G12: Manageable, not eliminated
B14: Sensitivity — Implied Enterprise Value (INR crore) = Adj. EBITDA × Multiple
B15: Base LTM adj. EBITDA (USD mn) | C15: 2188 | D15: Implied $35.9bn ÷ 16.4x (A4)
B16: Base LTM adj. EBITDA (INR cr) | C16: =C15*'08_Assumptions_Sources'!$D$9 -> 18372.636 | D16: Converted at FX 83.97 (A1)
B18: Implied EV (INR cr) Heat Grid
B19: EBITDA scenario \ Multiple → | C19: 13 | D19: 14 | E19: 15 | F19: 16.4 | G19: 17.5 | H19: Note
B20: Downside (-15%) | C20: =C$16*0.85*13 -> 203017.63 | D20: =C$16*0.85*14 -> 218634.37 | E20: =C$16*0.85*15 -> 234251.11 | F20: =C$16*0.85*16.4 -> 256114.55 | G20: =C$16*0.85*17.5 -> 273292.96
B21: Base (implied) | C21: =C$16*1*13 -> 238844.27 | D21: =C$16*1*14 -> 257216.9 | E21: =C$16*1*15 -> 275589.54 | F21: =C$16*1*16.4 -> 301311.23 | G21: =C$16*1*17.5 -> 321521.13 | H21: Deal EV ≈ ₹301,452 cr
B22: Upside (+15%) | C22: =C$16*1.15*13 -> 274670.91 | D22: =C$16*1.15*14 -> 295799.44 | E22: =C$16*1.15*15 -> 316927.97 | F22: =C$16*1.15*16.4 -> 346507.91 | G22: =C$16*1.15*17.5 -> 369749.3
B24: Actual deal consideration (EV, INR cr) | C24: =35.9*1000*'08_Assumptions_Sources'!$D$9 -> 301452.3 | D24: At 16.4x (base EBITDA) the model reproduces the actual deal EV — confirming the consideration sits at the upper-mid of the multiple range. Justifiable, not cheap.
B26: Fairness Conclusion
B27: JUSTIFIABLE, NOT CHEAP. The ~₹3.01 lakh-crore consideration prices Kellanova at 16.4x LTM adjusted EBITDA and a 44% premium — above the ~12–15x packaged-food trading range. The sensitivity grid shows the deal EV is only matched at ~16.4x on base EBITDA (or ~14x on +15% EBITDA), confirming Mars paid a full strategic-control price. It is defensible because the premium buys 100% control, two new billion-dollar brands, a doubling of Mars Snacking, and synergy option value that standalone multiples do not capture — and Mars' private balance sheet can fund and deleverage the all-cash structure. The fairness verdict is therefore positive but execution- and deleveraging-contingent.

Sheet 08_Assumptions_Sources
B2: Assumptions, Sources & Source Log
B3: Every sourced numerical line item in this workbook carries a Source ID (S##) referenced on its sheet. Conversions use the single FX assumption below.
B5: Key Assumptions
B6: Source ID | C6: Assumption | D6: Value / Basis | E6: Rationale | F6: Unit | G6: Source & URL | H6: Date accessed
B7: A1 | C7: FX rate USD/INR | D7: 83.97 | E7: Deal announcement date 14-Aug-2024 daily rate; used for ALL USD→INR conversions | F7: INR per USD | G7: exchange-rates.org — USD/INR history Aug 2024 | https://www.exchange-rates.org/exchange-rate-history/usd-inr-2024 | H7: 23-Jun-2026
B8: A2 | C8: INR crore definition | D8: 1 crore = 10,000,000 | E8: Indian numbering convention; principal display unit | F8: INR crore | G8: Standard Indian convention | H8: 23-Jun-2026
B9: A3 | C9: USD mn → INR crore factor | D9: =83.97/10 -> 8.397 | E9: FX(₹/USD) ÷ 10; converts USD million to INR crore (1 USD mn = ₹8.397 cr) | F9: ratio | G9: Derived from A1 (formula) | H9: 23-Jun-2026
B10: A4 | C10: Kellanova LTM adj. EBITDA (implied) | D10: =35.9/16.4*1000 -> 2189.0244 | E10: Back-solved from $35.9bn EV ÷ 16.4x stated multiple = ~$2.19bn | F10: USD mn | G10: Implied from Mars/Kellanova deal metrics (S2) | H10: 23-Jun-2026
B12: Source Log (all external & attached sources)
B13: Source ID | C13: Fact / data used | D13: Sheet ref. | E13: Source title | F13: Publisher | G13: URL | H13: Date accessed
B14: S1 | C14: Deal terms narrative; $83.50/share; $35.9bn; 44% premium; 16.4x EBITDA; financing; PMI; Dunzo case | D14: All | E14: Task-5: M&A Case Study (Mars-Kellanova & Reliance-Dunzo) | F14: Romit Banerjee (attached PDF) | G14: uploaded_attachments/.../Task-5_Romit-Shivadhwaj.pdf | H14: 23-Jun-2026
B15: S2 | C15: Acquisition terms, rationale, premium, EBITDA multiple, 180 markets, ~23k employees | D15: 02,03,05,06 | E15: Mars to Acquire Kellanova (official announcement) | F15: Mars, Incorporated | G15: https://www.mars.com/news-and-stories/press-releases/mars-to-acquire-kellanova | H15: 23-Jun-2026
B16: S3 | C16: FY2024 & FY2023 net sales, operating profit, net income, gross profit, cash, debt | D16: 04,05 | E16: Kellanova Reports Strong Results for Q4 & Full Year 2024 | F16: Kellanova (Q4-2024 results PDF) | G16: https://s203.q4cdn.com/897568180/files/doc_financials/2024/q4/K-Q4-2024-RESULTS.pdf | H16: 23-Jun-2026
B17: S4 | C17: Walmart 16% of net sales; top-5 customers 29%; employees; geographies; segments | D17: 03,04,08 | E17: Kellanova FY2024 Form 10-K | F17: Kellanova / SEC EDGAR | G17: https://www.sec.gov/Archives/edgar/data/1959348/000162828025007817/klg-20241228.htm | H17: 23-Jun-2026
B18: S5 | C18: $26bn senior notes; financing mix; leverage 1.2x→~4x→<3x; S&P downgrade A+→A | D18: 05,07,08 | E18: Mars debt financing / S&P rating action (deal commentary) | F18: Mars, Inc. / S&P Global Ratings (as cited in S1, S2) | G18: https://www.mars.com/news-and-stories/press-releases/mars-to-acquire-kellanova | H18: 23-Jun-2026
B19: S6 | C19: FX USD/INR = 83.97 on 14-Aug-2024 | D19: All conversions | E19: USD to INR Exchange Rate History for 2024 (Aug 14 = 83.971) | F19: Exchange-Rates.org | G19: https://www.exchange-rates.org/exchange-rate-history/usd-inr-2024 | H19: 23-Jun-2026
B20: S7 | C20: FX cross-check 14-Aug-2024 (83.879 / 83.96) | D20: Assumptions | E20: USD Historical Exchange Rates 14-Aug-2024 | F20: X-Rates | G20: https://www.x-rates.com/historical/?from=USD&amount=1&date=2024-08-14 | H20: 23-Jun-2026
B21: S8 | C21: Reliance wrote off ₹1,645 cr Dunzo investment; FY23 loss ₹1,800 cr; FY23 rev ₹226 cr; layoffs | D21: 02,06 | E21: Reliance Retail Writes Off ₹1645 Crore Dunzo Investment | F21: Angel One | G21: https://www.angelone.in/news/market-updates/reliance-retail-writes-off-1-645-crore-dunzo-investment-after-cash-burn-losses | H21: 23-Jun-2026
B22: S9 | C22: $200m / $240m round; 26% stake; Jan-2022; cash burn >₹100cr/month; app offline | D22: 02,06 | E22: Reliance writes off its $200 million investment in Dunzo | F22: The Economic Times | G22: https://economictimes.indiatimes.com/tech/startups/reliance-industries-writes-off-its-investment-in-dunzo/articleshow/123169856.cms | H22: 23-Jun-2026
B23: S10 | C23: Dunzo FY22 rev ₹54cr / loss ₹464cr; FY23 rev ₹89cr / loss ₹1,800cr+; store closures | D23: 02,06 | E23: Dunzo's Downfall Explained | F23: Outlook Business | G23: https://www.outlookbusiness.com/start-up/e-commerce/dunzos-downfall-explained-what-led-reliance-to-write-off-entire-200-million-stake-in-start-up | H23: 23-Jun-2026
