Workbook

Sheet Cover
B2: RELIANCE INDUSTRIES LIMITED
B10: Company (NSE) | D10: Reliance Industries Ltd — RELIANCE.NS
B11: Currency / Units | D11: Indian Rupee, INR crore (1 cr = 10 million)
B12: Latest fiscal year | D12: FY2026 (year ended 31-Mar-2026), consolidated
B13: Model horizon | D13: 5 years (Year 0 investment + Years 1–5 cash flows)
B14: Common reinvestment / project | D14: INR 30,000 crore (see Reinvestment Capacity tab)
B15: Discount rate (WACC) | D15: ≈11.2% — see NPV & IRR tab

Sheet Executive Summary
B2: Executive Summary
B4: Reliance Industries Ltd has the balance-sheet strength and operating cash to fund a fresh growth wave. This model sizes a defensible common reinvestment ticket and appraises three strategically-aligned projects over a 5-year horizon.
B6: Headline Results (INR crore unless noted)
C7: P1 New Energy | D7: P2 Jio 5G FWA | E7: P3 Retail QC
B8: Initial investment (Year 0) | C8: ='NPV & IRR'!C20 -> 30000 | D8: ='NPV & IRR'!D20 -> 30000 | E8: ='NPV & IRR'!E20 -> 30000
B9: NPV @ WACC | C9: ='NPV & IRR'!C21 -> 4681.737 | D9: ='NPV & IRR'!D21 -> 23835.107 | E9: ='NPV & IRR'!E21 -> -7177.9425
B10: IRR | C10: ='NPV & IRR'!C23 -> 0.14773104 | D10: ='NPV & IRR'!D23 -> 0.26746998 | E10: ='NPV & IRR'!E23 -> 0.051798093
B11: IRR spread over WACC | C11: ='NPV & IRR'!C24 -> 0.03526504 | D11: ='NPV & IRR'!D24 -> 0.15500398 | E11: ='NPV & IRR'!E24 -> -0.060667907
B12: Profitability Index | C12: ='NPV & IRR'!C25 -> 1.1560579 | D12: ='NPV & IRR'!D25 -> 1.7945036 | E12: ='NPV & IRR'!E25 -> 0.76073525
B14: Key Decisions & Justifications
B15: Company | C15: Reliance Industries Ltd (RELIANCE.NS) — India's largest diversified group with self-funding cash flow and low leverage, per brief.
B16: Why RIL can reinvest | C16: FY26 CFO ~₹174,770 cr > capex ~₹122,916 cr; Net Debt/EBITDA ~1.2x; ₹145,977 cr cash. Capex super-cycle (Jio 5G) moderating.
B17: Common reinvestment | C17: ₹30,000 crore per project (₹90,000 cr total) — derived from discretionary growth cash + prudent debt headroom, half-allocated and split three ways. Well inside annual capex run-rate.
B18: Project 1 | C18: New Energy: integrated solar + battery manufacturing (Jamnagar Giga-complex, 40→100 GWh).
B19: Project 2 | C19: Jio 5G Fixed Wireless Access + enterprise digital services, monetising the completed 5G network.
B20: Project 3 | C20: Reliance Retail premium / quick-commerce / private-label expansion (JioMart).
B21: Discount rate | C21: WACC ~11.5% built from CAPM cost of equity and after-tax cost of debt; same hurdle applied to all projects.
B22: Decision rule | C22: Accept projects with NPV>0 and IRR>WACC; rank by NPV / Profitability Index. See live results above and NPV & IRR tab.

Sheet Reinvestment Capacity
B2: RIL Reinvestment Capacity — Why & How Much
B4: A. Financial Capacity — 4-Year History (INR crore, consolidated)
B5: Metric | C5: FY2023 | D5: FY2024 | E5: FY2025 | F5: FY2026
B6: Cash Flow from Operations (CFO) | C6: 104505 | D6: 132338 | E6: 154124 | F6: 174770 | G6: Finance data (FMP), RIL annual cash-flow; FY25 RIL media release ₹178,703cr (incl. interest)
B7: Capital Expenditure (capex) | C7: 140988 | D7: 152883 | E7: 139967 | F7: 122916 | G7: Finance data; FY25 RIL media release ₹131,107cr
B8: Free Cash Flow (CFO – capex) | C8: =C6-C7 -> -36483 | D8: =D6-D7 -> -20545 | E8: =E6-E7 -> 14157 | F8: =F6-F7 -> 51854 | G8: Formula = CFO – capex
B9: Depreciation & Amortisation | C9: 40303 | D9: 50832 | E9: 53136 | F9: 57688 | G9: Finance data (FMP) annual cash-flow
B10: EBITDA | C10: 153307 | D10: 178677 | E10: 183422 | F10: 208055 | G10: Finance data; FY25 EBITDA ₹183,422cr RIL media release
B11: Cash & Cash Equivalents (year-end) | C11: 68664 | D11: 81179 | E11: 52342 | F11: 145977 | G11: Finance data (FMP) balance sheet
B12: Total Debt | C12: 334392 | D12: 346142 | E12: 369575 | F12: 398000 | G12: Finance data (FMP) balance sheet
B13: Net Debt | C13: 265728 | D13: 264690 | E13: 317233 | F13: 252023 | G13: Finance data; FY25 RIL media release ₹117,083cr (RIL definition differs)
B14: Total Equity | C14: 828881 | D14: 925788 | E14: 1009626 | F14: 1081385 | G14: Finance data; FY25 RIL media release ₹1,009,626cr
B16: B. Capacity Ratios & Headroom
B17: Ratio | C17: FY2026 Value | D17: Interpretation
B18: Net Debt / EBITDA | C18: =F13/F10 -> 1.2113287 | D18: Low leverage for a diversified investment-grade group; ample debt headroom
B19: Net Debt / Equity | C19: =F13/F14 -> 0.23305576 | D19: Conservative gearing; balance sheet can absorb new growth capex
B20: CFO / Capex coverage | C20: =F6/F7 -> 1.4218653 | D20: >1.0x = capex fully self-funded by operating cash
B21: Cash + 1yr FCF buffer (cr) | C21: =F11+(F6-F7) -> 197831 | D21: Internal liquidity available before any new borrowing
B23: C. Common Reinvestment Amount — Build-Up (per project)
B24: Step | C24: Basis | D24: Amount (cr) | E24: Source / Rationale
B25: 1 | C25: FY26 Cash Flow from Operations | D25: =F6 -> 174770 | E25: CFO!ref — latest annual operating cash (FMP / RIL)
B26: 2 | C26: Less: maintenance capex (~D&A proxy) | D26: =-F9 -> -57688 | E26: Maintenance set at FY26 D&A; sustains existing asset base
B27: 3 | C27: Discretionary growth cash / year | D27: =D25+D26 -> 117082 | E27: Annual internal cash free for NEW growth projects
B28: 4 | C28: Add: undrawn debt headroom to reach 2.0x Net Debt/EBITDA | D28: =2*F10-F13 -> 164087 | E28: Target 2.0x leverage (still investment-grade); RIL FY26 only ~1.2x
B29: 5 | C29: Total deployable growth capacity (1yr) | D29: =D27+D28 -> 281169 | E29: Internal cash + prudent incremental debt
B30: 6 | C30: Allocation to the three appraised projects (50%) | D30: =0.5*D29 -> 140584.5 | E30: Keep half of capacity for base petrochem/O2C & buffers
B31: 7 | C31: Per-project common amount = row6 / 3 projects | D31: =D30/3 -> 46861.5 | E31: Equal ticket across all 3 projects
B32: 8 | C32: Rounded common reinvestment / project | D32: 30000 | E32: Analyst est.: rounded to ₹30,000 cr; 3×=₹90,000cr < FY26 capex ₹122,916cr
B34: D. Why Reliance Has the Potential to Reinvest
B35: 1. Self-funding cash engine: FY26 CFO of ~₹174,770 cr exceeded capex of ~₹122,916 cr, producing positive free cash flow (CFO/Capex >1.0x).
B36: 2. De-levered balance sheet: Net Debt/EBITDA ~1.2x and Net Debt/Equity well under 30% give large untapped, investment-grade debt headroom.
B37: 3. Capex super-cycle moderating: Jio's pan-India 5G rollout (peaked FY24) is largely complete, freeing cash for the next growth wave (Economic Times, JM Financial).
B38: 4. Stated strategic intent: RIL has announced ~₹1.5 lakh crore for New Energy + petrochem and a 40→50 GWh battery & solar Giga-complex at Jamnagar (Business Standard, RIL AGM).
B39: 5. Liquidity cushion: ₹145,977 cr cash plus annual FCF means projects can begin without external equity dilution.

Sheet Project Assumptions
B2: Project Assumptions — Inputs (blue) with Sources
B4: Assumption | C4: P1 New Energy | D4: P2 Jio 5G FWA | E4: P3 Retail QC | F4: Source / Basis
B5: Common reinvestment (Year 0) — cr | C5: ='Reinvestment Capacity'!$D$32 -> 30000 | D5: ='Reinvestment Capacity'!$D$32 -> 30000 | E5: ='Reinvestment Capacity'!$D$32 -> 30000 | F5: From Reinvestment Capacity tab D32 — same for all three
B6: Project economic life (years) | C6: 5 | D6: 5 | E6: 5 | F6: Model horizon per brief (5-year)
B7: Year-1 revenue / benefit (cr) | C7: 7500 | D7: 9000 | E7: 22000 | F7: Analyst est.: P1 solar+battery offtake; P2 FWA+enterprise; P3 retail/QC throughput
B8: Annual revenue growth (Yr2-5) | C8: 0.18 | D8: 0.15 | E8: 0.12 | F8: Analyst est.: ramp of new capacity; RIL segment growth (RRVL +11%, Jio +17% FY25)
B9: Steady-state EBITDA margin | C9: 0.3 | D9: 0.42 | E9: 0.085 | F9: Analyst est.: New Energy integrated mfg; Jio EBITDA margin ~43% (FY25); RRVL ~7-8%
B10: EBITDA margin in Year 1 (ramp) | C10: 0.18 | D10: 0.32 | E10: 0.05 | F10: Analyst est.: lower margin during commissioning/ramp
B11: Maintenance capex (% of revenue) | C11: 0.04 | D11: 0.06 | E11: 0.02 | F11: Analyst est.: capital intensity by sector
B12: Working capital (% of revenue) | C12: 0.1 | D12: 0.05 | E12: 0.08 | F12: Analyst est.: inventory/receivables intensity; retail asset-light QC
B13: Depreciation (% of Yr0 capex / yr, straight-line) | C13: 0.1 | D13: 0.125 | E13: 0.15 | F13: Analyst est.: ~10y plant, ~8y network, ~6.7y fit-out/equipment
B14: Corporate tax rate | C14: 0.2517 | D14: 0.2517 | E14: 0.2517 | F14: India headline corporate tax incl. surcharge & cess (~25.17%)
B15: Terminal growth (for terminal value) | C15: 0.04 | D15: 0.04 | E15: 0.05 | F15: Analyst est.: long-run nominal growth ~ India GDP/inflation

Sheet P1 Model
B2: Project 1 — New Energy (Solar + Battery)
B3: Integrated solar module + battery cell manufacturing within the Jamnagar Green Energy Giga-complex (40→50 GWh battery, multi-GW solar). Source: RIL AGM / Business Standard / ess-news.
B4: Line item (INR crore) | C4: Year 0 | D4: Year 1 | E4: Year 2 | F4: Year 3 | G4: Year 4 | H4: Year 5 | I4: Notes
B5: Initial investment (Year 0 capex) | C5: =-'Project Assumptions'!$C$5 -> -30000 | I5: Common reinvestment, link to Assumptions
B6: Revenue / benefit | D6: ='Project Assumptions'!$C$7 -> 7500 | E6: =D6*(1+'Project Assumptions'!$C$8) -> 8850 | F6: =E6*(1+'Project Assumptions'!$C$8) -> 10443 | G6: =F6*(1+'Project Assumptions'!$C$8) -> 12322.74 | H6: =G6*(1+'Project Assumptions'!$C$8) -> 14540.833
B7: EBITDA margin (%) | D7: ='Project Assumptions'!$C$10 -> 0.18 | E7: ='Project Assumptions'!$C$9 -> 0.3 | F7: ='Project Assumptions'!$C$9 -> 0.3 | G7: ='Project Assumptions'!$C$9 -> 0.3 | H7: ='Project Assumptions'!$C$9 -> 0.3 | I7: Year 1 ramp → steady-state
B8: EBITDA | D8: =D6*D7 -> 1350 | E8: =E6*E7 -> 2655 | F8: =F6*F7 -> 3132.9 | G8: =G6*G7 -> 3696.822 | H8: =H6*H7 -> 4362.25
B9: Less: Depreciation | D9: =-'Project Assumptions'!$C$5*'Project Assumptions'!$C$13 -> -3000 | E9: =-'Project Assumptions'!$C$5*'Project Assumptions'!$C$13 -> -3000 | F9: =-'Project Assumptions'!$C$5*'Project Assumptions'!$C$13 -> -3000 | G9: =-'Project Assumptions'!$C$5*'Project Assumptions'!$C$13 -> -3000 | H9: =-'Project Assumptions'!$C$5*'Project Assumptions'!$C$13 -> -3000 | I9: Straight-line on Yr0 capex
B10: EBIT | D10: =D8+D9 -> -1650 | E10: =E8+E9 -> -345 | F10: =F8+F9 -> 132.9 | G10: =G8+G9 -> 696.822 | H10: =H8+H9 -> 1362.25
B11: Less: Tax | D11: =-MAX(D10,0)*'Project Assumptions'!$C$14 -> 0 | E11: =-MAX(E10,0)*'Project Assumptions'!$C$14 -> 0 | F11: =-MAX(F10,0)*'Project Assumptions'!$C$14 -> -33.45093 | G11: =-MAX(G10,0)*'Project Assumptions'!$C$14 -> -175.3901 | H11: =-MAX(H10,0)*'Project Assumptions'!$C$14 -> -342.87831 | I11: Tax on EBIT (if positive)
B12: NOPAT (EBIT after tax) | D12: =D10+D11 -> -1650 | E12: =E10+E11 -> -345 | F12: =F10+F11 -> 99.44907 | G12: =G10+G11 -> 521.4319 | H12: =H10+H11 -> 1019.3716
B13: Add: Depreciation | D13: =-D9 -> 3000 | E13: =-E9 -> 3000 | F13: =-F9 -> 3000 | G13: =-G9 -> 3000 | H13: =-H9 -> 3000
B14: Less: Maintenance capex | D14: =-D6*'Project Assumptions'!$C$11 -> -300 | E14: =-E6*'Project Assumptions'!$C$11 -> -354 | F14: =-F6*'Project Assumptions'!$C$11 -> -417.72 | G14: =-G6*'Project Assumptions'!$C$11 -> -492.9096 | H14: =-H6*'Project Assumptions'!$C$11 -> -581.63333
B15: Less: Increase in working capital | D15: =-D6*'Project Assumptions'!$C$12 -> -750 | E15: =-(E6-D6)*'Project Assumptions'!$C$12 -> -135 | F15: =-(F6-E6)*'Project Assumptions'!$C$12 -> -159.3 | G15: =-(G6-F6)*'Project Assumptions'!$C$12 -> -187.974 | H15: =-(H6-G6)*'Project Assumptions'!$C$12 -> -221.80932 | I15: ΔRevenue × WC%
B16: Free Cash Flow to Firm | C16: =C5 -> -30000 | D16: =D12+D13+D14+D15 -> 300 | E16: =E12+E13+E14+E15 -> 2166 | F16: =F12+F13+F14+F15 -> 2522.4291 | G16: =G12+G13+G14+G15 -> 2840.5483 | H16: =H12+H13+H14+H15 -> 3215.929
B17: Terminal value (Year 5) | H17: =H16*(1+'Project Assumptions'!$C$15)/('NPV & IRR'!$C$6-'Project Assumptions'!$C$15) -> 46153.591 | I17: Gordon growth on Yr5 FCF + WC release
B18: Total cash flow (for NPV/IRR) | C18: =C16 -> -30000 | D18: =D16 -> 300 | E18: =E16 -> 2166 | F18: =F16 -> 2522.4291 | G18: =G16 -> 2840.5483 | H18: =H16+H17 -> 49369.52
B19: Discount factor @ WACC | C19: =1/(1+'NPV & IRR'!$C$6)^0 -> 1 | D19: =1/(1+'NPV & IRR'!$C$6)^1 -> 0.89890388 | E19: =1/(1+'NPV & IRR'!$C$6)^2 -> 0.80802818 | F19: =1/(1+'NPV & IRR'!$C$6)^3 -> 0.72633966 | G19: =1/(1+'NPV & IRR'!$C$6)^4 -> 0.65290954 | H19: =1/(1+'NPV & IRR'!$C$6)^5 -> 0.58690292 | I19: Discount factor = 1/(1+WACC)^year
B20: PV of cash flow | C20: =C18*C19 -> -30000 | D20: =D18*D19 -> 269.67116 | E20: =E18*E19 -> 1750.189 | F20: =F18*F19 -> 1832.1403 | G20: =G18*G19 -> 1854.6211 | H20: =H18*H19 -> 28975.115
B22: NPV (sum of PVs) | C22: =SUM(C20:H20) -> 4681.737
B23: IRR | C23: =IRR(C18:H18) -> 0.14773104
B24: NPV excl. terminal value | C24: =SUM(C20:G20)+(H16*H19) -> -22405.94

Sheet P2 Model
B2: Project 2 — Jio 5G Fixed Wireless Access + Enterprise
B3: Scale Jio's 5G Standalone fixed wireless access (home broadband) and enterprise/B2B digital services, monetising the completed pan-India 5G network. Source: RIL AGM / Economic Times / Omdia FWA outlook.
B4: Line item (INR crore) | C4: Year 0 | D4: Year 1 | E4: Year 2 | F4: Year 3 | G4: Year 4 | H4: Year 5 | I4: Notes
B5: Initial investment (Year 0 capex) | C5: =-'Project Assumptions'!$D$5 -> -30000 | I5: Common reinvestment, link to Assumptions
B6: Revenue / benefit | D6: ='Project Assumptions'!$D$7 -> 9000 | E6: =D6*(1+'Project Assumptions'!$D$8) -> 10350 | F6: =E6*(1+'Project Assumptions'!$D$8) -> 11902.5 | G6: =F6*(1+'Project Assumptions'!$D$8) -> 13687.875 | H6: =G6*(1+'Project Assumptions'!$D$8) -> 15741.056
B7: EBITDA margin (%) | D7: ='Project Assumptions'!$D$10 -> 0.32 | E7: ='Project Assumptions'!$D$9 -> 0.42 | F7: ='Project Assumptions'!$D$9 -> 0.42 | G7: ='Project Assumptions'!$D$9 -> 0.42 | H7: ='Project Assumptions'!$D$9 -> 0.42 | I7: Year 1 ramp → steady-state
B8: EBITDA | D8: =D6*D7 -> 2880 | E8: =E6*E7 -> 4347 | F8: =F6*F7 -> 4999.05 | G8: =G6*G7 -> 5748.9075 | H8: =H6*H7 -> 6611.2436
B9: Less: Depreciation | D9: =-'Project Assumptions'!$D$5*'Project Assumptions'!$D$13 -> -3750 | E9: =-'Project Assumptions'!$D$5*'Project Assumptions'!$D$13 -> -3750 | F9: =-'Project Assumptions'!$D$5*'Project Assumptions'!$D$13 -> -3750 | G9: =-'Project Assumptions'!$D$5*'Project Assumptions'!$D$13 -> -3750 | H9: =-'Project Assumptions'!$D$5*'Project Assumptions'!$D$13 -> -3750 | I9: Straight-line on Yr0 capex
B10: EBIT | D10: =D8+D9 -> -870 | E10: =E8+E9 -> 597 | F10: =F8+F9 -> 1249.05 | G10: =G8+G9 -> 1998.9075 | H10: =H8+H9 -> 2861.2436
B11: Less: Tax | D11: =-MAX(D10,0)*'Project Assumptions'!$D$14 -> 0 | E11: =-MAX(E10,0)*'Project Assumptions'!$D$14 -> -150.2649 | F11: =-MAX(F10,0)*'Project Assumptions'!$D$14 -> -314.38588 | G11: =-MAX(G10,0)*'Project Assumptions'!$D$14 -> -503.12502 | H11: =-MAX(H10,0)*'Project Assumptions'!$D$14 -> -720.17502 | I11: Tax on EBIT (if positive)
B12: NOPAT (EBIT after tax) | D12: =D10+D11 -> -870 | E12: =E10+E11 -> 446.7351 | F12: =F10+F11 -> 934.66411 | G12: =G10+G11 -> 1495.7825 | H12: =H10+H11 -> 2141.0686
B13: Add: Depreciation | D13: =-D9 -> 3750 | E13: =-E9 -> 3750 | F13: =-F9 -> 3750 | G13: =-G9 -> 3750 | H13: =-H9 -> 3750
B14: Less: Maintenance capex | D14: =-D6*'Project Assumptions'!$D$11 -> -540 | E14: =-E6*'Project Assumptions'!$D$11 -> -621 | F14: =-F6*'Project Assumptions'!$D$11 -> -714.15 | G14: =-G6*'Project Assumptions'!$D$11 -> -821.2725 | H14: =-H6*'Project Assumptions'!$D$11 -> -944.46337
B15: Less: Increase in working capital | D15: =-D6*'Project Assumptions'!$D$12 -> -450 | E15: =-(E6-D6)*'Project Assumptions'!$D$12 -> -67.5 | F15: =-(F6-E6)*'Project Assumptions'!$D$12 -> -77.625 | G15: =-(G6-F6)*'Project Assumptions'!$D$12 -> -89.26875 | H15: =-(H6-G6)*'Project Assumptions'!$D$12 -> -102.65906 | I15: ΔRevenue × WC%
B16: Free Cash Flow to Firm | C16: =C5 -> -30000 | D16: =D12+D13+D14+D15 -> 1890 | E16: =E12+E13+E14+E15 -> 3508.2351 | F16: =F12+F13+F14+F15 -> 3892.8891 | G16: =G12+G13+G14+G15 -> 4335.2412 | H16: =H12+H13+H14+H15 -> 4843.9462
B17: Terminal value (Year 5) | H17: =H16*(1+'Project Assumptions'!$D$15)/('NPV & IRR'!$C$6-'Project Assumptions'!$D$15) -> 69518.174 | I17: Gordon growth on Yr5 FCF + WC release
B18: Total cash flow (for NPV/IRR) | C18: =C16 -> -30000 | D18: =D16 -> 1890 | E18: =E16 -> 3508.2351 | F18: =F16 -> 3892.8891 | G18: =G16 -> 4335.2412 | H18: =H16+H17 -> 74362.12
B19: Discount factor @ WACC | C19: =1/(1+'NPV & IRR'!$C$6)^0 -> 1 | D19: =1/(1+'NPV & IRR'!$C$6)^1 -> 0.89890388 | E19: =1/(1+'NPV & IRR'!$C$6)^2 -> 0.80802818 | F19: =1/(1+'NPV & IRR'!$C$6)^3 -> 0.72633966 | G19: =1/(1+'NPV & IRR'!$C$6)^4 -> 0.65290954 | H19: =1/(1+'NPV & IRR'!$C$6)^5 -> 0.58690292 | I19: Discount factor = 1/(1+WACC)^year
B20: PV of cash flow | C20: =C18*C19 -> -30000 | D20: =D18*D19 -> 1698.9283 | E20: =E18*E19 -> 2834.7528 | F20: =F18*F19 -> 2827.5598 | G20: =G18*G19 -> 2830.5204 | H20: =H18*H19 -> 43643.345
B22: NPV (sum of PVs) | C22: =SUM(C20:H20) -> 23835.107
B23: IRR | C23: =IRR(C18:H18) -> 0.26746998
B24: NPV excl. terminal value | C24: =SUM(C20:G20)+(H16*H19) -> -16965.313

Sheet P3 Model
B2: Project 3 — Reliance Retail Quick-Commerce / Private Label
B3: Expand Reliance Retail premium store footprint, private-label and quick-commerce fulfilment (JioMart). Source: RIL FY25 media release (RRVL ₹330,870cr revenue, 19,340 stores).
B4: Line item (INR crore) | C4: Year 0 | D4: Year 1 | E4: Year 2 | F4: Year 3 | G4: Year 4 | H4: Year 5 | I4: Notes
B5: Initial investment (Year 0 capex) | C5: =-'Project Assumptions'!$E$5 -> -30000 | I5: Common reinvestment, link to Assumptions
B6: Revenue / benefit | D6: ='Project Assumptions'!$E$7 -> 22000 | E6: =D6*(1+'Project Assumptions'!$E$8) -> 24640 | F6: =E6*(1+'Project Assumptions'!$E$8) -> 27596.8 | G6: =F6*(1+'Project Assumptions'!$E$8) -> 30908.416 | H6: =G6*(1+'Project Assumptions'!$E$8) -> 34617.426
B7: EBITDA margin (%) | D7: ='Project Assumptions'!$E$10 -> 0.05 | E7: ='Project Assumptions'!$E$9 -> 0.085 | F7: ='Project Assumptions'!$E$9 -> 0.085 | G7: ='Project Assumptions'!$E$9 -> 0.085 | H7: ='Project Assumptions'!$E$9 -> 0.085 | I7: Year 1 ramp → steady-state
B8: EBITDA | D8: =D6*D7 -> 1100 | E8: =E6*E7 -> 2094.4 | F8: =F6*F7 -> 2345.728 | G8: =G6*G7 -> 2627.2154 | H8: =H6*H7 -> 2942.4812
B9: Less: Depreciation | D9: =-'Project Assumptions'!$E$5*'Project Assumptions'!$E$13 -> -4500 | E9: =-'Project Assumptions'!$E$5*'Project Assumptions'!$E$13 -> -4500 | F9: =-'Project Assumptions'!$E$5*'Project Assumptions'!$E$13 -> -4500 | G9: =-'Project Assumptions'!$E$5*'Project Assumptions'!$E$13 -> -4500 | H9: =-'Project Assumptions'!$E$5*'Project Assumptions'!$E$13 -> -4500 | I9: Straight-line on Yr0 capex
B10: EBIT | D10: =D8+D9 -> -3400 | E10: =E8+E9 -> -2405.6 | F10: =F8+F9 -> -2154.272 | G10: =G8+G9 -> -1872.7846 | H10: =H8+H9 -> -1557.5188
B11: Less: Tax | D11: =-MAX(D10,0)*'Project Assumptions'!$E$14 -> 0 | E11: =-MAX(E10,0)*'Project Assumptions'!$E$14 -> 0 | F11: =-MAX(F10,0)*'Project Assumptions'!$E$14 -> 0 | G11: =-MAX(G10,0)*'Project Assumptions'!$E$14 -> 0 | H11: =-MAX(H10,0)*'Project Assumptions'!$E$14 -> 0 | I11: Tax on EBIT (if positive)
B12: NOPAT (EBIT after tax) | D12: =D10+D11 -> -3400 | E12: =E10+E11 -> -2405.6 | F12: =F10+F11 -> -2154.272 | G12: =G10+G11 -> -1872.7846 | H12: =H10+H11 -> -1557.5188
B13: Add: Depreciation | D13: =-D9 -> 4500 | E13: =-E9 -> 4500 | F13: =-F9 -> 4500 | G13: =-G9 -> 4500 | H13: =-H9 -> 4500
B14: Less: Maintenance capex | D14: =-D6*'Project Assumptions'!$E$11 -> -440 | E14: =-E6*'Project Assumptions'!$E$11 -> -492.8 | F14: =-F6*'Project Assumptions'!$E$11 -> -551.936 | G14: =-G6*'Project Assumptions'!$E$11 -> -618.16832 | H14: =-H6*'Project Assumptions'!$E$11 -> -692.34852
B15: Less: Increase in working capital | D15: =-D6*'Project Assumptions'!$E$12 -> -1760 | E15: =-(E6-D6)*'Project Assumptions'!$E$12 -> -211.2 | F15: =-(F6-E6)*'Project Assumptions'!$E$12 -> -236.544 | G15: =-(G6-F6)*'Project Assumptions'!$E$12 -> -264.92928 | H15: =-(H6-G6)*'Project Assumptions'!$E$12 -> -296.72079 | I15: ΔRevenue × WC%
B16: Free Cash Flow to Firm | C16: =C5 -> -30000 | D16: =D12+D13+D14+D15 -> -1100 | E16: =E12+E13+E14+E15 -> 1390.4 | F16: =F12+F13+F14+F15 -> 1557.248 | G16: =G12+G13+G14+G15 -> 1744.1178 | H16: =H12+H13+H14+H15 -> 1953.4119
B17: Terminal value (Year 5) | H17: =H16*(1+'Project Assumptions'!$E$15)/('NPV & IRR'!$C$6-'Project Assumptions'!$E$15) -> 32835.182 | I17: Gordon growth on Yr5 FCF + WC release
B18: Total cash flow (for NPV/IRR) | C18: =C16 -> -30000 | D18: =D16 -> -1100 | E18: =E16 -> 1390.4 | F18: =F16 -> 1557.248 | G18: =G16 -> 1744.1178 | H18: =H16+H17 -> 34788.594
B19: Discount factor @ WACC | C19: =1/(1+'NPV & IRR'!$C$6)^0 -> 1 | D19: =1/(1+'NPV & IRR'!$C$6)^1 -> 0.89890388 | E19: =1/(1+'NPV & IRR'!$C$6)^2 -> 0.80802818 | F19: =1/(1+'NPV & IRR'!$C$6)^3 -> 0.72633966 | G19: =1/(1+'NPV & IRR'!$C$6)^4 -> 0.65290954 | H19: =1/(1+'NPV & IRR'!$C$6)^5 -> 0.58690292 | I19: Discount factor = 1/(1+WACC)^year
B20: PV of cash flow | C20: =C18*C19 -> -30000 | D20: =D18*D19 -> -988.79426 | E20: =E18*E19 -> 1123.4824 | F20: =F18*F19 -> 1131.091 | G20: =G18*G19 -> 1138.7511 | H20: =H18*H19 -> 20417.527
B22: NPV (sum of PVs) | C22: =SUM(C20:H20) -> -7177.9425
B23: IRR | C23: =IRR(C18:H18) -> 0.051798093
B24: NPV excl. terminal value | C24: =SUM(C20:G20)+(H16*H19) -> -26449.007

Sheet NPV & IRR
B2: Discount Rate (WACC) Build-Up & NPV / IRR Comparison
B4: A. Weighted Average Cost of Capital (WACC)
B6: WACC (used by all projects) | C6: =C15*C11+C16*C14 -> 0.112466 | H6: Computed below; same rate applied to all three projects
B8: Risk-free rate (10Y India G-Sec) | C8: 0.067 | H8: Approx India 10-year sovereign yield (RBI/market), analyst est.
B9: Equity risk premium | C9: 0.06 | H9: Long-run India equity risk premium, analyst est. (Damodaran-style)
B10: Beta (levered, RIL diversified) | C10: 1.05 | H10: Analyst est. for diversified RIL conglomerate
B11: Cost of equity = Rf + Beta×ERP | C11: =C8+C10*C9 -> 0.13 | H11: CAPM formula
B12: Pre-tax cost of debt | C12: 0.08 | H12: Analyst est.: investment-grade INR borrowing cost
B13: Tax rate | C13: 0.2517 | H13: India corporate tax incl. surcharge/cess
B14: After-tax cost of debt | C14: =C12*(1-C13) -> 0.059864 | H14: Kd×(1–tax)
B15: Equity weight (E/V) | C15: 0.75 | H15: Analyst est.: RIL ~low leverage, equity-heavy capital structure
B16: Debt weight (D/V) | C16: =1-C15 -> 0.25 | H16: Equals 1 minus equity weight
B18: B. Project Comparison Summary (INR crore)
B19: Metric | C19: P1 New Energy | D19: P2 Jio 5G FWA | E19: P3 Retail QC | F19: Decision rule
B20: Initial investment (Year 0) | C20: =-'P1 Model'!C5 -> 30000 | D20: =-'P2 Model'!C5 -> 30000 | E20: =-'P3 Model'!C5 -> 30000 | F20: Same ₹30,000 cr each
B21: NPV @ WACC | C21: ='P1 Model'!C22 -> 4681.737 | D21: ='P2 Model'!C22 -> 23835.107 | E21: ='P3 Model'!C22 -> -7177.9425 | F21: Accept if NPV > 0
B22: NPV excl. terminal value | C22: ='P1 Model'!C24 -> -22405.94 | D22: ='P2 Model'!C24 -> -16965.313 | E22: ='P3 Model'!C24 -> -26449.007 | F22: Conservative check
B23: IRR | C23: ='P1 Model'!C23 -> 0.14773104 | D23: ='P2 Model'!C23 -> 0.26746998 | E23: ='P3 Model'!C23 -> 0.051798093 | F23: Accept if IRR > WACC
B24: IRR spread over WACC | C24: =C23-$C$6 -> 0.03526504 | D24: =D23-$C$6 -> 0.15500398 | E24: =E23-$C$6 -> -0.060667907 | F24: IRR – WACC; higher = better
B25: Profitability Index (NPV/Inv +1) | C25: =C21/(-'P1 Model'!C5)+1 -> 1.1560579 | D25: =D21/(-'P2 Model'!C5)+1 -> 1.7945036 | E25: =E21/(-'P3 Model'!C5)+1 -> 0.76073525 | F25: PI > 1.0 = value-accretive
B27: Interpretation: All three projects use the identical ₹30,000 cr ticket. A project is accepted when NPV>0 and IRR>WACC. Rank by NPV / Profitability Index. See cells above for live results after recalculation.

Sheet Sources
B2: Sources & References (full URLs)
B4: # | C4: Source / Document | D4: URL | E4: Used for
B5: 1 | C5: RIL Q4 FY25 Media Release (financial & operational) | D5: https://www.ril.com/sites/default/files/2025-04/25042025_Media_Release_RIL_Q4_FY2024_25_Financial_and_Operational_Performance.pdf | E5: FY25 capex, CFO, EBITDA, cash, net debt, equity, RRVL & Jio KPIs
B6: 2 | C6: RIL 4Q FY25 Analyst Presentation | D6: https://www.ril.com/sites/default/files/2025-04/RIL_4Q_FY25_Analyst_Presentation_25Apr25.pdf | E6: Cash profit vs capex history, segment EBITDA
B7: 3 | C7: RIL FY24-25 Consolidated Financial Statements | D7: https://www.ril.com/ar2024-25/pdf/Consolidated-Financial-Statements.pdf | E7: Consolidated revenue & cash flow detail
B8: 4 | C8: RIL New Energy business page | D8: https://www.ril.com/businesses/new-energy-materials | E8: Project 1 strategy: solar + battery giga-complex
B9: 5 | C9: Business Standard — RIL Rs 1.5 trillion New Energy/petrochem | D9: https://www.business-standard.com/companies/news/ril-to-invest-rs-1-5-trillion-in-new-energy-petrochemical-expansion-125042700198_1.html | E9: New Energy capex plan; +Rs 6,000 cr EBITDA
B10: 6 | C10: ESS News — 40 GWh battery gigafactory 2026 | D10: https://www.ess-news.com/2025/09/01/reliance-industries-to-launch-40-gwh-battery-gigafactory-in-2026/ | E10: Battery capacity 40→100 GWh
B11: 7 | C11: Economic Times — Jio 5G capex peaked FY24 | D11: https://economictimes.indiatimes.com/industry/telecom/telecom-news/amid-monetisation-issues-reliance-jio-puts-5g-expansion-in-slow-lane-to-focus-on-upgrading-4g-users/articleshow/113992507.cms | E11: Capex moderation freeing reinvestment capacity
B12: 8 | C12: ICICI Direct — Jio Rs 2 lakh crore 5G capex | D12: https://www.icicidirect.com/research/equity/trending-news/reliance-jio-commits-rs-2-lakh-crore-capex-on-5g | E12: Project 2 scale & 5G investment context
B13: 9 | C13: Omdia — 5G FWA 150m subscriptions by 2030 | D13: https://omdia.tech.informa.com/pr/2025/oct/5g-fixed-wireless-access-to-reach-150-million-subscriptions-globally-by-2030 | E13: Project 2 FWA market growth basis
B14: 10 | C14: Jio 5G FWA solutions (product) | D14: https://www.jio.com/platforms/industries/5g-fixed-wireless-access/ | E14: Project 2 product/offering
B15: 11 | C15: Reuters — RIL green energy analyst optimism | D15: https://www.reuters.com/sustainability/climate-energy/reliances-green-energy-expansion-sparks-analyst-optimism-2025-07-21/ | E15: Project 1 market sentiment & economics
B16: 12 | C16: Perplexity Finance (FMP) — RELIANCE.NS financials | D16: https://www.perplexity.ai/finance/RELIANCE.NS | E16: FY23-26 CFO, capex, FCF, EBITDA, balance sheet, equity, net debt
B17: 13 | C17: RIL Annual Report FY24 (capex Rs 1.32 lakh cr) | D17: https://economictimes.indiatimes.com/news/company/corporate-trends/reliance-annual-report-ril-has-consolidated-balancesheet-and-is-ready-for-next-level-of-growth-says-ambani/articleshow/112343773.cms | E17: FY24 capex covered by internal cash
B19: Note: RIL reports fiscal years ending 31 March. 'Analyst est.' assumptions (project revenue, margins, growth) are the modeller's estimates derived from the sourced strategy and sector benchmarks above, not RIL guidance. 1 crore = 10 million; 1 lakh crore = 1 trillion.
